{
  "animateLoading": true,
  "borderRadius": "{{appsmith.theme.borderRadius.appBorderRadius}}",
  "bottomRow": 44,
  "dynamicBindingPathList": [
    {
      "key": "truncateButtonColor"
    },
    {
      "key": "fontFamily"
    },
    {
      "key": "borderRadius"
    },
    {
      "key": "text"
    }
  ],
  "dynamicHeight": "AUTO_HEIGHT",
  "dynamicTriggerPathList": [],
  "fontFamily": "{{appsmith.theme.fontFamily.appFont}}",
  "fontSize": "1rem",
  "fontStyle": "BOLD",
  "isLoading": false,
  "isVisible": true,
  "key": "hirhbgkzca",
  "leftColumn": 3,
  "maxDynamicHeight": 9000,
  "minDynamicHeight": 4,
  "minWidth": 450,
  "mobileBottomRow": 39,
  "mobileLeftColumn": 3,
  "mobileRightColumn": 19,
  "mobileTopRow": 35,
  "needsErrorInfo": false,
  "originalBottomRow": 41,
  "originalTopRow": 37,
  "overflow": "NONE",
  "parentColumnSpace": 10.5625,
  "parentId": "0",
  "parentRowSpace": 10,
  "renderMode": "CANVAS",
  "responsiveBehavior": "fill",
  "rightColumn": 62,
  "shouldTruncate": false,
  "text": "Special Instructions: {{ (appsmith.store.orders || []).find(o => \n    String(o.order_id) === InputOrder.text || \n    o.customer.toLowerCase() === InputOrder.text.toLowerCase()\n)?.notes || \"\" }}",
  "textAlign": "LEFT",
  "textColor": "#231F20",
  "topRow": 40,
  "truncateButtonColor": "{{appsmith.theme.colors.primaryColor}}",
  "type": "TEXT_WIDGET",
  "version": 1,
  "widgetId": "4qumdl6nlv",
  "widgetName": "Text4"
}